sumdf/Database.py
sumdf/DatasUtility.py
sumdf/Dataset.py
sumdf/Logging.py
sumdf/Plots.py
sumdf/__init__.py
sumdf-0.1.0.dist-info/LICENSE
sumdf-0.1.0.dist-info/METADATA
sumdf-0.1.0.dist-info/WHEEL
sumdf-0.1.0.dist-info/top_level.txt
sumdf-0.1.0.dist-info/RECORD
